{
    "BIN_FCSKU_DATA": {
        "B004RIZKIS": {
            "asin": "B004RIZKIS",
            "height": {
                "unit": "IN",
                "value": 6.799999999999999
            },
            "length": {
                "unit": "IN",
                "value": 11.2
            },
            "name": "Dirt Devil Vacuum Filters for Central Vacuum (Aftermarket Generic Part) Replaces 8106-01",
            "quantity": 1,
            "weight": {
                "unit": "pounds",
                "value": 0.9
            },
            "width": {
                "unit": "IN",
                "value": 7.0
            }
        },
        "B008YNRUBW": {
            "asin": "B008YNRUBW",
            "height": {
                "unit": "IN",
                "value": 4.8
            },
            "length": {
                "unit": "IN",
                "value": 15.2
            },
            "name": "Wax Flameless LED Candles with Realistic Wick - 4 pack (Cream)",
            "quantity": 1,
            "weight": {
                "unit": "pounds",
                "value": 3.55
            },
            "width": {
                "unit": "IN",
                "value": 7.2
            }
        }
    },
    "EXPECTED_QUANTITY": 2,
    "image_fname": "422.jpg"
}